kickbase_analysis/__init__.py
kickbase_analysis/kickbase_analysis.py
kickbase_analysis/models/__init__.py
kickbase_analysis/models/trade.py
Kickbase_Analysis-0.0.3.dist-info/LICENSE
Kickbase_Analysis-0.0.3.dist-info/METADATA
Kickbase_Analysis-0.0.3.dist-info/WHEEL
Kickbase_Analysis-0.0.3.dist-info/top_level.txt
Kickbase_Analysis-0.0.3.dist-info/RECORD
