Metadata-Version: 2.1
Name: Kickbase-Analysis
Version: 0.0.3
Summary: Analysis framework for kickbase
Home-page: https://github.com/kevinskyba/kickbase-analysis
Author: kevinskyba
Author-email: kevinskyba@live.de
License: MIT
Platform: UNKNOWN
Requires-Dist: requests
Requires-Dist: kickbase-api
